MANIFEST.in
README.rst
setup.py
jw.mailfilter.egg-info/PKG-INFO
jw.mailfilter.egg-info/SOURCES.txt
jw.mailfilter.egg-info/dependency_links.txt
jw.mailfilter.egg-info/entry_points.txt
jw.mailfilter.egg-info/requires.txt
jw.mailfilter.egg-info/top_level.txt
mailfilter/__init__.py
mailfilter/action.py
mailfilter/app.py
mailfilter/classifier.py
mailfilter/content.py
mailfilter/filters.py
mailfilter/folder.py
mailfilter/header.py
mailfilter/imap.py
mailfilter/logging2.py
mailfilter/main.py
mailfilter/part.py
mailfilter/util.py
test/__init__.py
test/test10_body.py
test/test20_header.py
test/test30_rbl.py
test/test40_url.py
test/test50_action.py
test/body/negative.msg
test/body/positive_exact.msg
test/body/positive_upper.msg
test/body/positive_word.msg
test/header/encoded.msg
test/header/negative.msg
test/header/positive_exact.msg
test/header/positive_upper.msg
test/header/positive_word.msg
test/rbl/spam.msg
test/url/spam_negative.msg
test/url/spam_negative.msg~
test/url/spam_positive.msg