Metadata-Version: 1.1
Name: jw.mailfilter
Version: 0.5.14
Summary: IMAP mail filter
Home-page: https://pypi.python.org/pypi/jw.mailfilter
Author: Johnny Wezel
Author-email: dev-jay@wezel.name
License: GPL
Keywords: mail,imap,filter,spam
Platform: POSIX
Classifier: Development Status :: 4 - Beta
Classifier: Environment :: No Input/Output (Daemon)
Classifier: Intended Audience :: End Users/Desktop
Classifier: License :: OSI Approved :: GNU General Public License v3 or later (GPLv3+)
Classifier: Natural Language :: English
Classifier: Operating System :: POSIX
Classifier: Operating System :: Unix
Classifier: Programming Language :: Python :: 2
Classifier: Programming Language :: Python :: 2.7
Classifier: Programming Language :: Python :: 3
Classifier: Programming Language :: Python :: 3.4
